dbbasic_copypaste/__init__.py
dbbasic_copypaste/__main__.py
dbbasic_copypaste-0.1.0.dist-info/licenses/LICENSE
dbbasic_copypaste-0.1.0.dist-info/METADATA
dbbasic_copypaste-0.1.0.dist-info/WHEEL
dbbasic_copypaste-0.1.0.dist-info/entry_points.txt
dbbasic_copypaste-0.1.0.dist-info/top_level.txt
dbbasic_copypaste-0.1.0.dist-info/RECORD
